stile/__init__.py
stile/__main__.py
stile/app.py
stile/cli.py
stile/conf.py
stile/io.py
stile/metrics.py
stile/nodes.py
stile/pipeline.py
stile/simulation.py
stile/utils.py
stile/analysis/__init__.py
stile/analysis/hyperparameter_sweep_plots.py
stile-0.0.1.dist-info/licenses/LICENSE
stile-0.0.1.dist-info/METADATA
stile-0.0.1.dist-info/WHEEL
stile-0.0.1.dist-info/entry_points.txt
stile-0.0.1.dist-info/top_level.txt
stile-0.0.1.dist-info/RECORD
