Metadata-Version: 2.4
Name: stile
Version: 0.0.1
Summary: Python Boilerplate contains all the boilerplate you need to create a Python package.
Author-email: Harsh Sinha <mail.sinha.harsh@gmail.com>
Maintainer-email: Harsh Sinha <mail.sinha.harsh@gmail.com>
License-Expression: Apache-2.0
Project-URL: bugs, https://github.com/sinhaharsh/stile/issues
Project-URL: changelog, https://github.com/sinhaharsh/stile/blob/master/changelog.md
Project-URL: homepage, https://github.com/sinhaharsh/stile
Requires-Python: >=3.10
License-File: LICENSE
Requires-Dist: typer
Requires-Dist: scanpy
Requires-Dist: scipy
Requires-Dist: numpy
Requires-Dist: pandas
Requires-Dist: matplotlib
Requires-Dist: shapely
Requires-Dist: hdbscan
Provides-Extra: test
Requires-Dist: coverage; extra == "test"
Requires-Dist: pytest; extra == "test"
Requires-Dist: ruff; extra == "test"
Requires-Dist: ty; extra == "test"
Requires-Dist: ipdb; extra == "test"
Dynamic: license-file
